openlayer/__init__.py
openlayer/api.py
openlayer/constants.py
openlayer/datasets.py
openlayer/exceptions.py
openlayer/inference_pipelines.py
openlayer/llm_monitors.py
openlayer/models.py
openlayer/project_versions.py
openlayer/projects.py
openlayer/tasks.py
openlayer/utils.py
openlayer/version.py
openlayer/integrations/__init__.py
openlayer/integrations/langchain_callback.py
openlayer/model_runners/__init__.py
openlayer/model_runners/base_model.py
openlayer/model_runners/base_model_runner.py
openlayer/model_runners/environment.py
openlayer/model_runners/ll_model_runners.py
openlayer/model_runners/traditional_ml_model_runners.py
openlayer/model_runners/prediction_jobs/__init__.py
openlayer/model_runners/prediction_jobs/classification_prediction_job.py
openlayer/model_runners/prediction_jobs/regression_prediction_job.py
openlayer/schemas/__init__.py
openlayer/schemas/dataset_schemas.py
openlayer/schemas/inference_pipeline_schemas.py
openlayer/schemas/model_schemas.py
openlayer/schemas/project_schemas.py
openlayer/services/__init__.py
openlayer/services/data_streamer.py
openlayer/tracing/__init__.py
openlayer/tracing/enums.py
openlayer/tracing/steps.py
openlayer/tracing/tracer.py
openlayer/tracing/traces.py
openlayer/validators/__init__.py
openlayer/validators/base_validator.py
openlayer/validators/baseline_model_validators.py
openlayer/validators/commit_validators.py
openlayer/validators/dataset_validators.py
openlayer/validators/inference_pipeline_validators.py
openlayer/validators/model_validators.py
openlayer/validators/project_validators.py
openlayer_test-0.1.0a37.dist-info/LICENSE
openlayer_test-0.1.0a37.dist-info/METADATA
openlayer_test-0.1.0a37.dist-info/WHEEL
openlayer_test-0.1.0a37.dist-info/top_level.txt
openlayer_test-0.1.0a37.dist-info/RECORD
