Metadata-Version: 2.1
Name: openlayer-test
Version: 0.1.0a37
Summary: The official Python API library for Openlayer: the Testing and Debugging Platform for AI
Home-page: https://github.com/openlayer-ai/openlayer-python
Author: Unbox Inc.
Project-URL: Documentation, https://docs.openlayer.com/
Project-URL: Openlayer User Slack Group, https://l.linklyhq.com/l/1DG73
Keywords: MLOps,AI,Openlayer
Classifier: Operating System :: OS Independent
Classifier: Programming Language :: Python :: 3
Classifier: Programming Language :: Python :: 3 :: Only
Classifier: Programming Language :: Python :: 3.7
Classifier: Programming Language :: Python :: 3.8
Classifier: Programming Language :: Python :: 3.9
Classifier: Programming Language :: Python :: Implementation :: CPython
Classifier: Topic :: Scientific/Engineering :: Artificial Intelligence
Classifier: Topic :: Software Development :: Libraries
Requires-Python: >=3.7
License-File: LICENSE
Requires-Dist: pyyaml
Requires-Dist: marshmallow
Requires-Dist: marshmallow-oneofschema
Requires-Dist: openai >=1.12.0
Requires-Dist: pandas
Requires-Dist: pybars3
Requires-Dist: requests-toolbelt
Requires-Dist: requests >=2.28.2
Requires-Dist: tabulate
Requires-Dist: tqdm
Requires-Dist: urllib3 >=1.26.14
